{"name": "TRABALHA_EVENTUALMENTE <= 0.5", "children": [{"name": "IDADE <= 0.5", "children": [{"name": "IDADE <= 0.5", "children": [{"name": "ETNIA_N_DECLARADA <= 0.5", "children": [{"name": " class: B <= 0.5", "children": []}, {"name": " class: B <= 0.5", "children": []}]}, {"name": "N_TRABALHA <= 0.5", "children": [{"name": " class: B <= 0.5", "children": []}, {"name": " class: B <= 0.5", "children": []}]}]}, {"name": "IDADE <= 0.5", "children": [{"name": "IDADE <= 0.5", "children": [{"name": " class: C <= 0.5", "children": []}, {"name": " class: C <= 0.5", "children": []}]}, {"name": "IDADE <= 0.5", "children": [{"name": " class: C <= 0.5", "children": []}, {"name": " class: B <= 0.5", "children": []}]}]}]}, {"name": "IDADE <= 0.5", "children": [{"name": "IDADE <= 0.5", "children": [{"name": "FIES <= 0.5", "children": [{"name": " class: C <= 0.5", "children": []}, {"name": " class: C <= 0.5", "children": []}]}, {"name": "ESTUDANDO_8H_A_12H <= 0.5", "children": [{"name": " class: C <= 0.5", "children": []}, {"name": " class: C <= 0.5", "children": []}]}]}, {"name": "ETNIA_N_DECLARADA <= 0.5", "children": [{"name": "MAIOR_PARTE_PRIVADA <= 0.5", "children": [{"name": " class: C <= 0.5", "children": []}, {"name": " class: C <= 0.5", "children": []}]}, {"name": " class: B <= 0.5", "children": []}]}]}]}